app_model/__init__.py
app_model/_app.py
app_model/py.typed
app_model/backends/__init__.py
app_model/backends/qt/__init__.py
app_model/backends/qt/_qaction.py
app_model/backends/qt/_qkeybindingedit.py
app_model/backends/qt/_qkeymap.py
app_model/backends/qt/_qmainwindow.py
app_model/backends/qt/_qmenu.py
app_model/backends/qt/_util.py
app_model/expressions/__init__.py
app_model/expressions/_context.py
app_model/expressions/_context_keys.py
app_model/expressions/_expressions.py
app_model/registries/__init__.py
app_model/registries/_commands_reg.py
app_model/registries/_keybindings_reg.py
app_model/registries/_menus_reg.py
app_model/registries/_register.py
app_model/types/__init__.py
app_model/types/_action.py
app_model/types/_base.py
app_model/types/_command_rule.py
app_model/types/_constants.py
app_model/types/_icon.py
app_model/types/_keybinding_rule.py
app_model/types/_menu_rule.py
app_model/types/_utils.py
app_model/types/_keys/__init__.py
app_model/types/_keys/_key_codes.py
app_model/types/_keys/_keybindings.py
app_model/types/_keys/_standard_bindings.py
app_model-0.5.0.dist-info/METADATA
app_model-0.5.0.dist-info/WHEEL
app_model-0.5.0.dist-info/licenses/LICENSE
app_model-0.5.0.dist-info/RECORD
